pyepicollect/__init__.py
pyepicollect/api.py
pyepicollect/auth.py
tests/__init__.py
tests/test_auth.py
pyepicollect-5.1.0.dist-info/METADATA
pyepicollect-5.1.0.dist-info/WHEEL
pyepicollect-5.1.0.dist-info/top_level.txt
pyepicollect-5.1.0.dist-info/RECORD
