Metadata-Version: 2.1
Name: pyepicollect
Version: 5.1.0
Summary: Read EpiCollect 5 data from python
Home-page: UNKNOWN
Author: Rodrigo E. Principe
Author-email: fitoprincipe82@gmail.com
License: UNKNOWN
Keywords: epicollect epicollect5 database
Platform: UNKNOWN
Classifier: Programming Language :: Python :: 3
Classifier: Programming Language :: Python :: 3.6
Requires-Dist: requests
Provides-Extra: dev
Provides-Extra: docs
Provides-Extra: testing
Requires-Dist: pytest (>=4.2.1) ; extra == 'testing'
